asaca/__init__.py
asaca/__main__.py
asaca/cli.py
asaca/gui.py
asaca/inference.py
asaca/cognition/__init__.py
asaca/cognition/cognition_inference.py
asaca/cognition/dictionary_builder.py
asaca/cognition/feature_extractor.py
asaca/cognition/model_training.py
asaca/cognition/model_training_improved.py
asaca/cognition/nlp_utils.py
asaca/speech_tools/__init__.py
asaca/speech_tools/config.py
asaca/speech_tools/config.yaml
asaca/speech_tools/diarize.py
asaca/speech_tools/pause.py
asaca/speech_tools/praat_bridge.py
asaca/speech_tools/syllable.py
asaca/speech_tools/textgrid_utils.py
asaca-0.1.3.dist-info/licenses/LICENSE
pyctcdecoder/__init__.py
asaca-0.1.3.dist-info/METADATA
asaca-0.1.3.dist-info/WHEEL
asaca-0.1.3.dist-info/entry_points.txt
asaca-0.1.3.dist-info/top_level.txt
asaca-0.1.3.dist-info/RECORD
