Metadata-Version: 2.4
Name: ASACA
Version: 0.1.3
Summary: Automatic Speech Analysis for Cognitive Assessment
Author-email: Xinbo Yang <xyang2@tcd.ie>
License: Apache-2.0
Requires-Python: >=3.10
License-File: LICENSE
Requires-Dist: numpy>=1.24
Requires-Dist: pandas>=1.5
Requires-Dist: scipy>=1.10
Requires-Dist: joblib>=1.3
Requires-Dist: tqdm>=4.66
Requires-Dist: sympy>=1.12
Requires-Dist: torch
Requires-Dist: torchvision
Requires-Dist: torchaudio
Requires-Dist: scikit-learn>=1.4
Requires-Dist: transformers>=4.38
Requires-Dist: datasets>=2.18
Requires-Dist: evaluate>=0.4
Requires-Dist: safetensors>=0.4
Requires-Dist: soundfile>=0.12
Requires-Dist: librosa>=0.10
Requires-Dist: resampy>=0.4
Requires-Dist: ctc-segmentation>=1.7
Requires-Dist: webrtcvad
Requires-Dist: praat-parselmouth>=0.4
Requires-Dist: pronouncing>=0.2
Requires-Dist: pyctcdecode>=0.5
Requires-Dist: jiwer>=3.0
Requires-Dist: pyannote.audio>=3.1
Requires-Dist: pyannote.core>=5.0
Requires-Dist: matplotlib>=3.7
Requires-Dist: pillow>=10.2
Requires-Dist: shap
Requires-Dist: psutil>=5.9
Requires-Dist: openpyxl>=3.1
Requires-Dist: nltk
Requires-Dist: PyYAML>=6.0
Requires-Dist: pyqt5
Requires-Dist: pyqtgraph
Requires-Dist: reportlab
Provides-Extra: gpu
Requires-Dist: torch; extra == "gpu"
Requires-Dist: torchaudio; extra == "gpu"
Requires-Dist: pyannote.audio; extra == "gpu"
Provides-Extra: dev
Requires-Dist: ruff; extra == "dev"
Requires-Dist: black; extra == "dev"
Requires-Dist: pre-commit; extra == "dev"
Requires-Dist: pytest; extra == "dev"
Requires-Dist: pytest-cov; extra == "dev"
Requires-Dist: mypy; extra == "dev"
Requires-Dist: pytest-qt; extra == "dev"
Requires-Dist: PyQt5; extra == "dev"
Provides-Extra: docs
Requires-Dist: mkdocs-material; extra == "docs"
Requires-Dist: mkdocstrings[python]; extra == "docs"
Dynamic: license-file
